Tauri.toml
build_hook.py
rxconfig.py
.web/build/client/404.html
.web/build/client/__spa-fallback.html
.web/build/client/favicon.ico
.web/build/client/index.css
.web/build/client/index.html
.web/build/client/assets/_404_._index-DWWI2tkp.js
.web/build/client/assets/__reflex_global_styles-Djy-KIkS.css
.web/build/client/assets/_index-Cbwpol86.js
.web/build/client/assets/chunk-JMJ3UQ3L-Cy1y8aTa.js
.web/build/client/assets/emotion-react.browser.esm-DhKrZlEN.js
.web/build/client/assets/entry.client-CiPEKrvP.js
.web/build/client/assets/esm-BbkH1dhB.js
.web/build/client/assets/manifest-30222e0c.js
.web/build/client/assets/react-dom-WWniO_zt.js
.web/build/client/assets/reflex-env-irNVy4st.js
.web/build/client/assets/rolldown-runtime-CkEfyhlV.js
.web/build/client/assets/root-Dq-yOT9r.js
.web/node_modules/monaco-editor/dev/vs/assets/css.worker-CgWp-mpq.js
.web/node_modules/monaco-editor/dev/vs/assets/editor.worker-DbHNojjm.js
.web/node_modules/monaco-editor/dev/vs/assets/html.worker-Dp8eKPfv.js
.web/node_modules/monaco-editor/dev/vs/assets/json.worker-CvNsV1ln.js
.web/node_modules/monaco-editor/dev/vs/assets/ts.worker-ClNbeHrN.js
.web/node_modules/monaco-editor/min/vs/assets/css.worker-HnVq6Ewq.js
.web/node_modules/monaco-editor/min/vs/assets/editor.worker-Be8ye1pW.js
.web/node_modules/monaco-editor/min/vs/assets/html.worker-B51mlPHg.js
.web/node_modules/monaco-editor/min/vs/assets/json.worker-DKiEKt88.js
.web/node_modules/monaco-editor/min/vs/assets/ts.worker-CMbG-7ft.js
assets/favicon.ico
assets/index.css
capabilities/default.toml
pycodium/__init__.py
pycodium/__main__.py
pycodium/constants.py
pycodium/main.py
pycodium/menu.py
pycodium/pycodium.py
pycodium/state.py
pycodium/version.py
pycodium/components/__init__.py
pycodium/components/activity_bar.py
pycodium/components/editor_area.py
pycodium/components/editor_tabs.py
pycodium/components/file_explorer.py
pycodium/components/hotkey_watcher.py
pycodium/components/menu_events.py
pycodium/components/monaco.py
pycodium-0.3.1.dist-info/METADATA
pycodium-0.3.1.dist-info/WHEEL
pycodium-0.3.1.dist-info/entry_points.txt
pycodium-0.3.1.dist-info/licenses/LICENSE
pycodium-0.3.1.dist-info/RECORD
