Metadata-Version: 2.4
Name: pycodium
Version: 0.3.1
Summary: A Python IDE written in Python
Project-URL: Changelog, https://github.com/jan-mue/pycodium/releases
Project-URL: Documentation, https://github.com/jan-mue/pycodium#readme
Project-URL: Issues, https://github.com/jan-mue/pycodium/issues
Project-URL: Source, https://github.com/jan-mue/pycodium
Author: Jan Müller
License: MIT License
License-File: LICENSE
Classifier: Development Status :: 3 - Alpha
Classifier: Intended Audience :: Developers
Classifier: License :: OSI Approved :: MIT License
Classifier: Operating System :: OS Independent
Classifier: Programming Language :: Python
Classifier: Programming Language :: Python :: 3 :: Only
Classifier: Programming Language :: Python :: 3.10
Classifier: Programming Language :: Python :: 3.11
Classifier: Programming Language :: Python :: 3.12
Classifier: Programming Language :: Python :: 3.13
Classifier: Programming Language :: Python :: Implementation :: CPython
Requires-Python: <3.14,>=3.10
Requires-Dist: aiofiles==25.1.0
Requires-Dist: charset-normalizer==3.4.4
Requires-Dist: granian==2.6.1
Requires-Dist: psutil==7.2.1
Requires-Dist: pydantic==2.12.5
Requires-Dist: pygments==2.19.2
Requires-Dist: pytauri-wheel==0.8.0
Requires-Dist: reflex==0.8.25
Requires-Dist: typer==0.21.1
Requires-Dist: typing-extensions==4.15.0
Requires-Dist: watchfiles==1.1.1
